ape_chainstack/__init__.py
ape_chainstack/providers.py
ape_chainstack/py.typed
ape_chainstack/utils.py
ape_chainstack/version.py
ape_chainstack-0.8.0a1.dist-info/LICENSE
ape_chainstack-0.8.0a1.dist-info/METADATA
ape_chainstack-0.8.0a1.dist-info/WHEEL
ape_chainstack-0.8.0a1.dist-info/top_level.txt
ape_chainstack-0.8.0a1.dist-info/RECORD
