Metadata-Version: 2.1
Name: ape-chainstack
Version: 0.8.0a1
Summary: ape-chainstack: Ape Ecosystem Plugin for Chainstack
Home-page: https://github.com/ApeWorX/ape-chainstack
Author: ApeWorX Ltd.
Author-email: admin@apeworx.io
License: Apache-2.0
Keywords: ethereum
Classifier: Development Status :: 3 - Alpha
Classifier: Intended Audience :: Developers
Classifier: License :: OSI Approved :: Apache Software License
Classifier: Natural Language :: English
Classifier: Operating System :: MacOS
Classifier: Operating System :: POSIX
Classifier: Programming Language :: Python :: 3
Classifier: Programming Language :: Python :: 3.9
Classifier: Programming Language :: Python :: 3.10
Classifier: Programming Language :: Python :: 3.11
Classifier: Programming Language :: Python :: 3.12
Requires-Python: >=3.9,<4
License-File: LICENSE
Requires-Dist: eth-ape <0.9,>=0.8
Provides-Extra: dev
Requires-Dist: pytest >=6.0 ; extra == 'dev'
Requires-Dist: pytest-xdist ; extra == 'dev'
Requires-Dist: pytest-cov ; extra == 'dev'
Requires-Dist: hypothesis <7.0,>=6.2.0 ; extra == 'dev'
Requires-Dist: black <24,>=23.12.0 ; extra == 'dev'
Requires-Dist: mypy <2,>=1.7.1 ; extra == 'dev'
Requires-Dist: types-setuptools ; extra == 'dev'
Requires-Dist: flake8 <7,>=6.1.0 ; extra == 'dev'
Requires-Dist: flake8-breakpoint <2,>=1.1.0 ; extra == 'dev'
Requires-Dist: flake8-print <6,>=5.0.0 ; extra == 'dev'
Requires-Dist: isort <6,>=5.10.1 ; extra == 'dev'
Requires-Dist: mdformat >=0.7.17 ; extra == 'dev'
Requires-Dist: mdformat-gfm >=0.3.5 ; extra == 'dev'
Requires-Dist: mdformat-frontmatter >=0.4.1 ; extra == 'dev'
Requires-Dist: mdformat-pyproject >=0.0.1 ; extra == 'dev'
Requires-Dist: setuptools ; extra == 'dev'
Requires-Dist: wheel ; extra == 'dev'
Requires-Dist: twine ; extra == 'dev'
Requires-Dist: commitizen ; extra == 'dev'
Requires-Dist: pre-commit ; extra == 'dev'
Requires-Dist: pytest-watch ; extra == 'dev'
Requires-Dist: IPython ; extra == 'dev'
Requires-Dist: ipdb ; extra == 'dev'
Provides-Extra: lint
Requires-Dist: black <24,>=23.12.0 ; extra == 'lint'
Requires-Dist: mypy <2,>=1.7.1 ; extra == 'lint'
Requires-Dist: types-setuptools ; extra == 'lint'
Requires-Dist: flake8 <7,>=6.1.0 ; extra == 'lint'
Requires-Dist: flake8-breakpoint <2,>=1.1.0 ; extra == 'lint'
Requires-Dist: flake8-print <6,>=5.0.0 ; extra == 'lint'
Requires-Dist: isort <6,>=5.10.1 ; extra == 'lint'
Requires-Dist: mdformat >=0.7.17 ; extra == 'lint'
Requires-Dist: mdformat-gfm >=0.3.5 ; extra == 'lint'
Requires-Dist: mdformat-frontmatter >=0.4.1 ; extra == 'lint'
Requires-Dist: mdformat-pyproject >=0.0.1 ; extra == 'lint'
Provides-Extra: release
Requires-Dist: setuptools ; extra == 'release'
Requires-Dist: wheel ; extra == 'release'
Requires-Dist: twine ; extra == 'release'
Provides-Extra: test
Requires-Dist: pytest >=6.0 ; extra == 'test'
Requires-Dist: pytest-xdist ; extra == 'test'
Requires-Dist: pytest-cov ; extra == 'test'
Requires-Dist: hypothesis <7.0,>=6.2.0 ; extra == 'test'
